salt_mill-1.1.0.dist-info/DESCRIPTION.rst
salt_mill-1.1.0.dist-info/METADATA
salt_mill-1.1.0.dist-info/RECORD
salt_mill-1.1.0.dist-info/WHEEL
salt_mill-1.1.0.dist-info/metadata.json
salt_mill-1.1.0.dist-info/top_level.txt
saltmill/__init__.py
saltmill/core.py
