Metadata-Version: 2.0
Name: salt-mill
Version: 1.1.0
Summary: Saltstack API Client for Humans
Home-page: https://github.com/glasslion/salt-mill
Author: Leo Zhou
Author-email: glasslion@gmail.com
License: BSD
Keywords: salt-mill
Platform: UNKNOWN
Classifier: Development Status :: 2 - Pre-Alpha
Classifier: Intended Audience :: Developers
Classifier: License :: OSI Approved :: BSD License
Classifier: Natural Language :: English
Classifier: Programming Language :: Python :: 2
Classifier: Programming Language :: Python :: 2.6
Classifier: Programming Language :: Python :: 2.7
Classifier: Programming Language :: Python :: 3
Classifier: Programming Language :: Python :: 3.3
Classifier: Programming Language :: Python :: 3.4
Requires-Dist: salt-pepper (>=0.4.0)
Requires-Dist: six
